LICENSE.txt
README.md
setup.py
Topsis_Mudrika_102017143.egg-info/PKG-INFO
Topsis_Mudrika_102017143.egg-info/SOURCES.txt
Topsis_Mudrika_102017143.egg-info/dependency_links.txt
Topsis_Mudrika_102017143.egg-info/entry_points.txt
Topsis_Mudrika_102017143.egg-info/requires.txt
Topsis_Mudrika_102017143.egg-info/top_level.txt
source/func.py