Metadata-Version: 2.1
Name: Topsis-Mudrika-102017143
Version: 1.0.3
Summary: This is a Python library for handling problems related to Multiple Criteria Decision Making(MCDM)
Home-page: UNKNOWN
Author: Mudrika Jain
Author-email: jainmudrika29@gmail.com
License: MIT
Platform: UNKNOWN
Classifier: License :: OSI Approved :: MIT License
Classifier: Programming Language :: Python :: 3.6
Classifier: Programming Language :: Python :: 3.7
Classifier: Programming Language :: Python :: 3.8
License-File: LICENSE.txt
